givenpy/__init__.py
givenpy-1.0.5.dist-info/METADATA
givenpy-1.0.5.dist-info/WHEEL
givenpy-1.0.5.dist-info/licenses/LICENSE
givenpy-1.0.5.dist-info/RECORD
