Metadata-Version: 2.4
Name: givenpy
Version: 1.0.5
Summary: A simple micro BDD framework for Python
Project-URL: Documentation, https://github.com/tadas-subonis/givenpy
Project-URL: Repository, https://github.com/tadas-subonis/givenpy
Project-URL: Bug Tracker, https://github.com/tadas-subonis/givenpy/issues
Author-email: Tadas Subonis <tadas.subonis@gmail.com>
License: MIT
License-File: LICENSE
Keywords: BDD,framework,micro,test,testing,unittest
Classifier: Development Status :: 4 - Beta
Classifier: Intended Audience :: Developers
Classifier: License :: OSI Approved :: MIT License
Classifier: Programming Language :: Python :: 3
Classifier: Programming Language :: Python :: 3.8
Classifier: Topic :: Software Development :: Libraries
Classifier: Topic :: Software Development :: Testing
Classifier: Topic :: Utilities
Requires-Python: >=3.8
